{
  "id": "03",
  "moduleId": "03-roles",
  "title": "Additional Duties & Specialized Roles",
  "estimatedTime": "18 min",
  "phase1_prime": {
    "breathing": {
      "intro": "This chapter reveals the invisible architecture. The roles that serve by disappearing.",
      "instructions": "Take a slow breath. You're learning about sacred service—the kind no one sees when it's done perfectly. The foundation that holds everything."
    },
    "story": {
      "content": "Day 2, 4:45 AM. Most volunteers were still asleep in their hotel rooms. But not the Meditation Assists.\n\nSarah entered the dark ballroom. The first meditation would begin at 6 AM. She'd be stationed in the Blue section for the next three hours, watching 200 souls drop into altered states. Ready to respond if someone needed help. Ready to hold space for whatever emerged.\n\nShe'd trained for this. Read the protocol guide until she could recite it. Understood the difference between emotional release and medical crisis. Knew when to intervene and when to simply witness. This wasn't just a role—it was sacred responsibility. These people were about to journey into the quantum field, and she was their anchor in physical reality.\n\nAcross the ballroom, the Room Reset team had been working since 10 PM. After everyone left the previous night, they'd entered the empty space and begun transforming it. Moving 47 gravity chairs into tomorrow's positions. Placing 89 reserved signs according to the detailed seat map. Adjusting rows. Creating pathways. Every chair precisely positioned. Every sign exactly where Medical said it needed to be.\n\nMarcus, the Room Reset Lead, understood something most people didn't: the physical space IS the energetic container. When participants walked in at 6 AM and found their section perfectly organized, when the person with mobility issues discovered their chair exactly where accessibility required it, when everything just worked—that invisible perfection created felt safety. The container held because the details were perfect.\n\nBy 5:30 AM, the Signs Lead was doing final rounds. Walking every section, verifying every reserved sign, replacing two that had been damaged, ensuring crystal clarity. Most participants would never notice these signs. But the 89 people they served would notice if they were missing. Invisible excellence.\n\nOutside the ballroom, the Coherence Healing Ballroom Lead was coordinating with venue staff for tomorrow's CH session. Setting up the flow pattern so 100+ HealEEs could enter smoothly, receive sacred healing, and exit without disruption. Positioning materials. Planning timing. Making sure the choreography served both practical needs and energetic integrity.\n\nSection Leads were already in position by 5:45 AM, scanning their areas one final time. Everything ready? Any last-minute adjustments needed? Medical access pathways clear? Participants would arrive in 15 minutes.\n\nThese weren't the celebrated roles. No one applauded when gravity chairs were positioned perfectly. Participants didn't thank the MA who held silent space during their breakthrough. The Signs Lead's work was only visible when it failed.\n\nBut without these roles? The whole system would collapse.\n\n6:00 AM. Doors opened. Participants streamed in, found their perfectly prepared sections, settled into their seats, and dropped into meditation without a thought about the infrastructure supporting them.\n\nThat was the point.\n\nAfter the meditation ended, Sarah—the MA—quietly returned to her room. Three hours of holding space, two gentle interventions, one signal to Medical for precautionary monitoring. No one knew what she'd done. No one would thank her specifically.\n\nBut she knew. The work was sacred whether anyone saw it or not.\n\nLater that day, a first-time volunteer asked her: 'How do you stay motivated doing work no one notices?'\n\nSarah smiled. 'That's exactly why it matters. When we serve what's invisible—set up rooms at midnight, hold space during meditation, coordinate healing logistics—we're training ourselves to see energy, to trust what can't be measured, to find meaning in service itself rather than recognition.'\n\n'This IS the consciousness work. Not separate from it. Not preparation for it. This is it.'\n\nAdditional Duties are consciousness training disguised as logistics.",
      "hook": "The invisible roles that make transformation possible. You're learning to serve what cannot be seen."
    },
    "learningObjectives": [
      "Master Meditation Assist protocol as energetic holding combined with practical intervention",
      "Understand Room Reset as setting the sacred container through physical precision",
      "Learn Coherence Healing coordination as serving the healing journey with logistical grace",
      "Recognize how Additional Duties ARE spiritual practice, not separate from it"
    ]
  },
  "phase2_immerse": {
    "sections": [
      {
        "title": "Meditation Assist: Sacred Witnessing in Altered States",
        "content": "**MEDITATION ASSIST (MA) IS WHERE CONSCIOUSNESS MEETS PROTOCOL**\n\n**The Sacred Function:**\nYou're stationed in the ballroom during every guided meditation, holding dual awareness:\n• **Physical safety:** Watching for medical needs, falls, dangerous situations\n• **Energetic holding:** Witnessing breakthroughs, anchoring the field, trusting the process\n\nThis is advanced work. You're the calm presence while others journey into the unknown.\n\n---\n\n**CORE RESPONSIBILITIES:**\n\n**During Setup (Before Meditation):**\n• Arrive early (usually 15-30 minutes before meditation starts)\n• Position yourself strategically in your assigned section—clear sight lines, easy access to participants\n• Check in with other MAs and Medical team via Telegram\n• Ground yourself: breathe, center, set intention\n• Ensure your phone is on silent but accessible (you may need to signal Medical)\n• Quick visual scan: any hazards? clear pathways? gravity chairs stable?\n\n**During Meditation (The Core Work):**\n\n**Your stance:**\n• Stand or sit where you can see your entire section\n• Stay grounded in your body—this isn't the time for YOU to journey\n• Soft, panoramic awareness—not staring intensely at individuals\n• Trust your intuition—if something feels off, pay attention\n\n**What you're watching for:**\n\n**Emotional release (usually not an intervention):**\n• Quiet crying, tears streaming\n• Body trembling, shaking\n• Facial expressions of emotion\n• Deep breathing patterns\n• Small movements, rocking\n\n**When to observe without intervening:**\n• Person seems present and grounded even while crying/shaking\n• They're not disrupting others around them\n• They appear to be processing, not in crisis\n• Body language suggests release, not panic\n\n**Your response:** Hold space. Stay calm. Send grounding energy. Be ready to help if needed but don't interrupt their process.\n\n**Situations requiring closer attention:**\n• Loud sobbing that disrupts others (move closer, assess, possibly gentle touch on shoulder or whispered \"I'm here\")\n• Intense shaking that looks like they might fall off chair (position yourself to catch if needed)\n• Vocalizations that seem distressed vs. ecstatic (discern: are they in crisis or breakthrough?)\n• Sudden stillness after intense movement (check they're still breathing)\n\n**Medical emergencies requiring immediate intervention:**\n• Seizure (follow seizure protocol—see Module 4)\n• Falling from chair/loss of balance\n• Difficulty breathing, choking\n• Chest pain, signs of heart issue\n• Loss of consciousness\n• Visible injury\n• Extreme panic attack (hyperventilating, can't breathe, terror)\n\n**Your response:** Move quickly but calmly. Signal Medical via Telegram or direct communication. Provide immediate support (prevent falling, clear space, calm reassurance). Follow emergency protocols.\n\n**After Meditation:**\n• Stay in position until Dr. Joe officially ends the session and participants begin leaving\n• Be available for anyone who approaches with questions or concerns\n• Debrief with fellow MAs and Medical team via Telegram if anything significant occurred\n• Document anything important (injuries, medical interventions, etc.)\n\n---\n\n**THE CONSCIOUSNESS PRINCIPLES OF MA WORK:**\n\n**1. Discernment, not judgment**\nYou're not evaluating whether their experience is 'good' or 'bad.' You're discerning: is this safe? That's your only question.\n\nSomeone crying might be having their deepest healing.\nSomeone laughing might be having their biggest breakthrough.\nSomeone shaking might be releasing trauma stored in their body.\n\nYour job isn't to decide if they're 'doing it right.' Your job is to ensure they're physically safe while they do it.\n\n**2. Non-interference with process**\nDon't intervene just because something looks intense. Transformation IS intense.\n\nThe person shaking violently might be exactly where they need to be.\nThe person sobbing might be releasing decades of stored emotion.\nThe person making sounds might be moving energy that's been stuck.\n\nIntervene only when:\n• They're in physical danger\n• They're disrupting others' ability to do their work\n• They're asking for help\n\nOtherwise? Hold space. Trust their process. BE the calm.\n\n**3. Grounded presence**\nYou're the anchor. When everyone else is in the quantum field, you're in physical reality.\n\nThis means:\n• You don't meditate while you're MA (save that for when you're a participant)\n• You stay in your body, grounded, present\n• Your nervous system regulation affects the field—stay calm\n• You're the reference point for 'safe' in the room\n\nIf you're anxious, others feel it.\nIf you're grounded, others feel that too.\n\n**4. Invisible service**\nWhen you do MA well, no one knows you were there.\n\nThe participant who almost fell but didn't because you were positioned perfectly?\nThe person having a breakthrough who felt your calm presence nearby?\nThe medical situation you caught early and handled smoothly?\n\nThey might not even remember you. That's perfect.\n\nYour effectiveness is measured by how seamlessly everything flows, not by how visible you are.\n\n**5. Sacred trust**\nPeople are profoundly vulnerable during meditation. They're:\n• Dropping into altered states\n• Releasing control\n• Trusting the process\n• Hoping for transformation\n\nThey're trusting that someone is watching. That they're safe. That if something goes wrong, someone competent will help.\n\nYou're that someone.\n\nDon't be on your phone. Don't chat with other volunteers. Don't zone out.\n\nBE present. HOLD space. STAY ready.\n\nThis is sacred responsibility.\n\n---\n\n**COMMON MA SCENARIOS:**\n\n**Scenario 1: Loud crying that's disrupting others**\n• Approach quietly, kneel beside them\n• Gentle touch on shoulder or hand\n• Soft whisper: \"I'm here. You're safe. Let me know if you need anything.\"\n• Assess: Are they grounded enough to stay? Or do they need to step out?\n• If stepping out: whisper \"Would you like to move to the quiet area? I'll walk with you.\"\n• Don't force—offer support, let them choose\n\n**Scenario 2: Intense shaking, looks like they might fall**\n• Move close, position yourself to catch if needed\n• Don't restrain or stop the shaking—it's energetic release\n• If they start sliding off chair, gently support them\n• If shaking becomes full-body seizure: seizure protocol (Module 4)\n• Stay calm, ground yourself, hold space\n\n**Scenario 3: Panic attack (hyperventilating, terrified)**\n• Approach quickly but calmly\n• Get down to their eye level: \"I'm here. You're safe. Breathe with me.\"\n• Model slow breathing: breathe with them until they start to regulate\n• Soft reassurance: \"You're okay. I'm staying right here.\"\n• If not improving: signal Mental Health team or Medical\n• Offer to walk them out to quiet area if needed\n\n**Scenario 4: Medical emergency (seizure, fall, injury)**\n• Move immediately\n• Signal Medical via Telegram: \"Medical to [section color] - [brief description]\"\n• Follow emergency protocol (see Module 4)\n• Stay with participant until Medical arrives\n• Brief Medical clearly on what happened\n• Document the incident\n\n**Scenario 5: Someone signals you for help**\n• Approach quickly but calmly\n• Kneel down, quiet voice: \"What do you need?\"\n• Listen, assess, respond appropriately\n• Bathroom? Walk them out, tell them how to return\n• Feeling overwhelmed? Offer quiet area\n• Medical issue? Get Medical team\n• Just needs reassurance? Provide it, stay briefly, return to station\n\n---\n\n**MA SELF-CARE:**\n\nMA duty is demanding. You're:\n• Standing for hours\n• Holding high alertness\n• Witnessing intense experiences\n• Managing your own nervous system\n\n**How to sustain yourself:**\n\n**Before your MA shift:**\n• Eat something sustaining\n• Hydrate well\n• Use bathroom\n• Ground yourself: breathing, centering, intention-setting\n• Arrive early, don't rush\n\n**During your shift:**\n• Shift your weight, move subtly (you can stay present while avoiding locked knees)\n• Take deep breaths periodically\n• If you need a 2-minute break, signal another MA to cover\n• Stay hydrated (small sips of water are fine if not disruptive)\n\n**After your shift:**\n• Take 10-15 minutes to decompress\n• Shake out your body, release held tension\n• Hydrate, eat if needed\n• Process with other MAs if you witnessed something intense\n• Rest before your next duty\n\n**Emotional labor:**\nYou're witnessing people's pain, breakthroughs, releases. That's heavy.\n\nDon't carry it alone. Debrief with other MAs. Talk to Mental Health team if something affected you. This is why MA is typically assigned to experienced volunteers—it requires emotional maturity.\n\n---\n\n**KEY PRINCIPLES FOR MA EXCELLENCE:**\n\n• **Discern, don't judge:** Is it safe? That's your only question.\n• **Trust the process:** Transformation looks messy. Don't interrupt unless necessary.\n• **Stay grounded:** You're the anchor while others journey.\n• **Invisible service:** Done well, no one knows you were there.\n• **Sacred responsibility:** People trust you to keep them safe while they surrender.\n\nMeditation Assist is where logistics meet consciousness. Where protocol meets presence. Where service becomes sacred.\n\nYou're holding the space for transformation. That's holy work."
      },
      {
        "title": "Room Reset: Setting the Sacred Container Through Physical Precision",
        "content": "**ROOM RESET IS CONSCIOUSNESS WORK DISGUISED AS FURNITURE MOVING**\n\n**The Sacred Function:**\nAfter everyone leaves each evening, the Room Reset team transforms the ballroom for the next day. This isn't just logistics—it's creating the physical container that holds the energetic field.\n\n**The consciousness principle:**\nWhen participants walk in tomorrow and everything just works—their gravity chair is perfectly positioned, their reserved sign is clear, their section is organized, the space feels coherent—that invisible perfection creates felt safety.\n\nThey can surrender more deeply because the container is trustworthy.\n\nYou're setting that container. Through furniture. Through signs. Through physical detail.\n\n---\n\n**THE ROOM RESET PROCESS:**\n\n**Timing:**\n• Usually begins after evening session ends (often 9-10 PM)\n• Can go until midnight or later depending on setup complexity\n• Requires physical stamina and attention to detail when you're tired\n\n**Team Structure:**\n\n**Room Reset Lead:**\n• Coordinates overall setup\n• Has the Master Plan (detailed seat map, gravity chair positions, reserved signs)\n• Directs volunteers on what goes where\n• Troubleshoots issues\n• Communicates with Group Leads, Medical team, HSL about special needs\n\n**Signs Lead:**\n• Manages all reserved signage throughout event\n• Tracks which signs go where each day\n• Replaces damaged signs\n• Ensures signs are clear, visible, accurate\n• Coordinates with Medical and HSL on reservation needs\n\n**Greeter/Room volunteers:**\n• Assigned to specific sections (usually their daytime Greeter section)\n• Execute Room Reset in their assigned area\n• Move gravity chairs, place signs, adjust rows\n• Know their section layout intimately\n\n---\n\n**WHAT ROOM RESET INVOLVES:**\n\n**Gravity Chair Positioning:**\n• Heavy, reclining chairs for participants with medical/mobility needs\n• Must be positioned according to Master Plan (Medical team determines placement based on safety, accessibility, sight lines)\n• Exact placement matters: too close to aisle = tripping hazard; too far back = participant can't see\n• Secured properly so they don't slide during use\n• Checked for stability and function\n\n**Reserved Signs:**\n• Small signs placed on specific seats for participants with accommodations\n• \"Reserved\" with participant name or ID\n• Must match Medical team's accommodation list exactly\n• Placed clearly on seat (visible but not falling off)\n• Double-checked against Master Plan\n• Tracked by Signs Lead (damaged signs replaced immediately)\n\n**Section Adjustments:**\n• Sometimes row spacing needs adjustment for wheelchair access\n• Sometimes entire sections rearrange based on group size changes\n• Sometimes stage proximity changes for HealEEs or special accommodations\n• Greeter/Room volunteers execute changes per Room Reset Lead direction\n\n**Daily Variations:**\n• Not every day is identical\n• Coherence Healing days have different setup\n• Special meditations might require stage area changes\n• Participant additions/cancellations affect layout\n• You're executing THE PLAN, not improvising\n\n---\n\n**THE CONSCIOUSNESS PRINCIPLES OF ROOM RESET:**\n\n**1. Precision as sacred service**\nEvery gravity chair positioned perfectly. Every sign exactly where it belongs. Every row spaced correctly.\n\nWhy?\n\nBecause tomorrow morning, someone with severe mobility issues will arrive and find their chair waiting. Positioned for safety. Close to bathroom access. Not blocking others. They'll sit down and think: \"They thought of everything. I can relax.\"\n\nThat relaxation? You created it. At 11 PM. When you were exhausted. By moving a chair three feet to the left because the plan said so.\n\nThat's consciousness work.\n\n**2. Invisible excellence**\nWhen Room Reset is done perfectly, no one notices.\n\nParticipants walk in the next day and everything is just... right. They don't think about who stayed late. They don't thank you specifically. They just experience a space that works.\n\nThat's the goal.\n\nYour excellence is measured by how effortless the space feels. How coherent. How trustworthy.\n\nIf participants consciously notice the setup, something went wrong.\n\n**3. Serving what you won't experience**\nYou're setting up gravity chairs you'll never sit in.\nYou're placing reserved signs for people you haven't met.\nYou're creating accessibility for needs that aren't yours.\n\nThis is advanced service: working for others' benefit with no direct personal gain.\n\nThe participant who gets that gravity chair won't know your name. But their comfort, their safety, their ability to participate fully—you created that.\n\n**4. Trust the system**\nRoom Reset Lead has the Master Plan. Medical team provided gravity chair specs. Signs Lead confirmed reservations. Group Leads approved section layouts.\n\nYour job isn't to redesign the system. It's to execute it with precision.\n\nFollow the plan. Trust that the upstream coordination was done correctly. Execute your piece with excellence.\n\n**5. Late-night dedication**\nThis role requires sacrifice.\n\nYou've been at the event since early morning. You're tired. Everyone else is leaving. And you're staying late to move chairs.\n\nWhy?\n\nBecause tomorrow's transformation depends on tonight's preparation.\n\nThe participant who has their breakthrough tomorrow—partly because the space felt safe, coherent, organized? Your late-night work contributed to that.\n\nService isn't convenient. It's devotional.\n\n---\n\n**PRACTICAL ROOM RESET EXECUTION:**\n\n**When instructions are posted:**\n• Room Reset Lead posts setup plan in Telegram or provides printouts\n• Usually includes: section diagrams, gravity chair positions (by row/seat number), reserved sign placements, any special notes\n• Read the ENTIRE plan before starting\n• If anything is unclear, ask Room Reset Lead BEFORE executing\n\n**Greeter/Room volunteer execution:**\n• Go to your assigned section\n• Bring necessary materials (gravity chairs from storage, signs from Signs Lead, tools if needed)\n• Follow the plan exactly:\n  - \"Move gravity chair to Blue section, Row 5, Seat 3\" → Do exactly that\n  - \"Place reserved sign on Yellow section, Row 8, Seat 12\" → Do exactly that\n• Double-check your work against the plan\n• If you finish your section, ask Room Reset Lead if other sections need help\n• Notify Room Reset Lead when your section is complete\n\n**Quality checks:**\n• Gravity chairs stable and functional\n• Reserved signs visible and secure\n• Aisles clear (no tripping hazards)\n• Section looks organized and coherent\n• Everything matches the Master Plan\n\n**Communication:**\n• If something doesn't match the plan (wrong row numbers, not enough chairs, damaged sign), notify Room Reset Lead immediately\n• Don't improvise solutions—coordinate with the Lead\n• Use Telegram for updates: \"Blue section complete, all gravity chairs positioned and checked\"\n\n---\n\n**SIGNS LEAD SPECIFIC ROLE:**\n\n**Throughout the event:**\n• Track all reserved signs (usually 80-120 signs across all sections)\n• Know where each sign should be each day (changes based on medical needs, accommodations)\n• Replace damaged/missing signs immediately\n• Coordinate with Medical team and HSL on new reservation requests\n• Ensure signs are clear, professional, and accurately placed\n\n**Daily:**\n• Provide signs to Greeter/Room volunteers for their sections\n• Do final walk-through before participants arrive—verify all signs correct\n• Be available during day if signs need adjustment\n• Collect signs that are no longer needed (participant cancellation, accommodation change)\n\n**Why this role matters:**\nA missing reserved sign means someone with a medical need can't find their seat. An incorrect sign means someone sits in a seat that was designated for someone else's accommodation. \n\nSigns seem small. But they represent accessibility, dignity, and safety. Your detailed tracking ensures people get the accommodations they need.\n\n---\n\n**ROOM RESET CHALLENGES & SOLUTIONS:**\n\n**Challenge: Instructions unclear**\n• Don't guess—ask Room Reset Lead for clarification\n• Better to pause and get it right than execute incorrectly\n\n**Challenge: Gravity chair is damaged/won't recline**\n• Report to Room Reset Lead immediately\n• They'll coordinate replacement with venue or Medical team\n• Don't use a faulty chair—someone's safety depends on it working\n\n**Challenge: Running out of reserved signs**\n• Notify Signs Lead\n• They'll make more or coordinate with Room Reset Lead\n• Never leave a reservation unmarked\n\n**Challenge: Physical exhaustion (chairs are heavy, it's late)**\n• Work with others—move chairs in pairs if needed\n• Take breaks when necessary\n• Communicate if you need help: \"Blue section needs 2 more people for gravity chairs—they're heavier than expected\"\n\n**Challenge: Conflicting information (Group Lead says different plan than Room Reset Lead)**\n• Default to Room Reset Lead's Master Plan—they coordinate with everyone upstream\n• If genuinely conflicting, connect Group Lead and Room Reset Lead to resolve\n• Don't be stuck in the middle—escalate to leadership\n\n---\n\n**KEY PRINCIPLES FOR ROOM RESET EXCELLENCE:**\n\n• **Precision matters:** Three feet left vs. three feet right can mean safety vs. hazard\n• **Follow the plan:** You're executing coordinated upstream decisions\n• **Invisible excellence:** Done perfectly, no one notices you were there\n• **Serve what you won't experience:** The chairs you set up aren't for you\n• **Late-night devotion:** Tomorrow's transformation depends on tonight's preparation\n\nRoom Reset is consciousness training: learning to serve with precision, devotion, and zero attachment to recognition.\n\nYou're building the physical container that holds sacred space.\n\nThat's holy work disguised as furniture moving."
      },
      {
        "title": "Coherence Healing Coordination: Sacred Logistics of the Healing Journey",
        "content": "**COHERENCE HEALING LEADS SERVE TRANSFORMATION THEY WON'T PERSONALLY EXPERIENCE**\n\n**The Sacred Function:**\nTwo Coherence Healing Leads coordinate the complex logistics of CH sessions:\n• **CH Ballroom Lead:** Inside the healing space, managing HealEE flow and Healer coordination\n• **CH Outside Ballroom Lead:** Outside the healing space, managing HealEE waiting area and entry timing\n\nThis is advanced service: orchestrating healing for 100+ people with grace, precision, and devotional attention.\n\n---\n\n**WHY CH COORDINATION MATTERS:**\n\nCoherence Healing sessions involve:\n• 100-150 HealEEs (participants receiving healing)\n• 40-60 Healers (volunteers giving healing)\n• Strict timing (sessions run on schedule, can't extend indefinitely)\n• Multiple rounds (HealEEs rotate through different Healers)\n• Emotional intensity (HealEEs are vulnerable, seeking healing for serious conditions)\n• Sacred space (this is profound work, logistics must serve the healing)\n\nWithout coordination: chaos. Long waits. Missed sessions. Confusion. Anxiety.\n\nWith excellent coordination: smooth flow. Timely entry. Clear guidance. Trust.\n\nCH Leads make the difference.\n\n---\n\n**CH BALLROOM LEAD (Inside the Healing Space):**\n\n**Before the session:**\n• Coordinate with HSL on HealEE list (who's scheduled, any special needs)\n• Set up healing tables/spaces according to plan\n• Brief Healers on timing, flow, any special instructions\n• Ensure materials are in place (sheets, pillows, sanitization supplies)\n• Test sound system if Healers need music/guidance\n• Walk the space: Is it sacred? Clean? Ready?\n\n**During the session:**\n\n**Managing HealEE entry:**\n• Coordinate with Outside Lead on timing: \"Ready for next group of 10\"\n• Greet HealEEs warmly as they enter: \"Welcome. Your Healer is ready.\"\n• Direct HealEEs to their assigned Healer/table\n• Handle any immediate questions: \"How long will this take?\" \"What if I need to use the bathroom?\"\n• Ensure smooth flow—no bottlenecks at entrance\n\n**Supporting the healing process:**\n• Monitor the room without intruding on healing\n• Be available if Healers need assistance (supplies, timing clarification, etc.)\n• Handle any issues that arise (HealEE becomes distressed, medical concern, etc.)\n• Maintain sacred space: keep energy calm, voices low, presence grounded\n\n**Managing HealEE exit:**\n• Signal when healing round is complete\n• Guide HealEEs to exit: \"When you're ready, you can exit through that door. Take your time.\"\n• Ensure they know where to go next (back to seats, quiet area, next round if applicable)\n• Transition Healers to next round if multi-round session\n\n**After the session:**\n• Thank Healers, acknowledge their service\n• Coordinate cleanup with Room Reset if needed\n• Debrief with Outside Lead: How did flow work? Any improvements for next time?\n• Document any issues for HSL\n\n---\n\n**CH OUTSIDE BALLROOM LEAD (Managing the Waiting Area):**\n\n**Before the session:**\n• Set up HealEE waiting area (chairs, water, tissues, calm space)\n• Have HealEE schedule/list (who's in which round, any special timing)\n• Coordinate with Ballroom Lead on entry timing\n• Be present early so HealEEs arrive to a calm, ready space\n\n**During the session:**\n\n**Managing HealEE arrivals:**\n• Greet HealEEs as they arrive: \"Welcome. You're right on time. Have a seat and we'll call you in shortly.\"\n• Check them in against schedule\n• Provide orientation: \"You'll be called in groups of 10. When it's your turn, we'll guide you inside. The session lasts about 20 minutes.\"\n• Answer questions calmly\n• Manage nervous energy: \"It's normal to feel nervous. Many people find it deeply peaceful.\"\n\n**Coordinating entry timing:**\n• Communicate with Ballroom Lead via Telegram: \"Next group ready? We have 12 waiting.\"\n• When Ballroom Lead signals ready, call HealEEs: \"Sarah, John, Maria... your Healers are ready. Follow me.\"\n• Walk them to entrance, hand them off to Ballroom Lead\n• Return to waiting area for next group\n\n**Supporting waiting HealEEs:**\n• Provide calm, grounded presence\n• Handle questions: \"What will happen in there?\" \"Is this safe?\" \"What if I get emotional?\"\n• Provide reassurance: \"You're in good hands. The Healers are trained and caring.\"\n• If someone arrives late: assess if they can still be accommodated, coordinate with Ballroom Lead\n• If someone is very anxious: offer extra support, maybe brief grounding practice\n\n**After the session:**\n• Ensure all HealEEs entered (none missed)\n• Clean up waiting area\n• Debrief with Ballroom Lead\n• Note any issues for HSL\n\n---\n\n**THE CONSCIOUSNESS PRINCIPLES OF CH COORDINATION:**\n\n**1. You're serving sacred moments**\nEach HealEE is coming for profound healing. This might be:\n• Their last hope for a serious illness\n• Their attempt to heal childhood trauma\n• Their prayer for a miracle\n\nYour logistics serve their sacred journey.\n\nWhen you guide them calmly to their Healer, you're reducing their anxiety.\nWhen the flow is smooth, they can surrender more fully.\nWhen you're grounded, they feel safer.\n\nYour organizational excellence creates space for their healing.\n\n**2. Calm amidst intensity**\nHealEEs are often nervous, emotional, vulnerable. Some are crying. Some are scared. Some are desperately hopeful.\n\nYour calm nervous system helps them regulate.\n\nDon't match their anxiety. Don't rush. Don't get flustered.\n\nStay grounded. Breathe. Move deliberately. Speak softly.\n\nYou're the anchor. They need you to be steady.\n\n**3. Invisible orchestration**\nWhen CH coordination works perfectly, HealEEs simply experience smooth flow. They don't think about logistics. They think about healing.\n\nThat's the goal.\n\nYour excellence is measured by how effortless the experience feels.\n\nThe complex coordination, the timing management, the troubleshooting—that's all behind the scenes. What HealEEs experience is: \"This was so well organized. I felt safe and cared for.\"\n\nThat's invisible leadership.\n\n**4. Collaboration between Inside and Outside Leads**\nThis role only works if both Leads communicate constantly:\n• \"Ready for next group?\"\n• \"We have someone running late—can we hold 3 minutes?\"\n• \"HealEE in distress—Mental Health needed\"\n• \"Flow working well—great timing\"\n\nYou're two parts of one system. Constant coordination.\n\n**5. Serving transformation you won't experience**\nYou're coordinating healing you're not receiving. You're watching others get Coherence Healing while you manage logistics.\n\nThis is advanced consciousness work: serving others' transformation without needing to experience it yourself.\n\nThe HealEE who has their profound healing moment? Your logistics contributed. You'll never know specifically how. And that's perfect.\n\n---\n\n**CH LEAD CHALLENGES & SOLUTIONS:**\n\n**Challenge: HealEE arrives very late**\n• Assess: Can they still be accommodated this round?\n• Coordinate with Ballroom Lead: \"One late arrival—can we add them or should they join next session?\"\n• Communicate kindly to HealEE: \"Your session was scheduled for 2 PM. We can try to fit you in now, or you're confirmed for the 4 PM session.\"\n• Don't make them feel bad—they might have gotten lost or had an issue\n\n**Challenge: More HealEEs show up than scheduled**\n• Coordinate with Ballroom Lead and HSL: \"We have 5 extra HealEEs—not on the schedule. Can we accommodate?\"\n• If yes: fit them in\n• If no: \"I apologize for the confusion. Let me coordinate with the team to get you scheduled for another session.\"\n• Escalate to HSL for scheduling resolution\n\n**Challenge: HealEE becomes very emotional in waiting area**\n• Provide calm presence: \"It's okay to feel emotional. This is important to you.\"\n• Offer tissue, water, space to breathe\n• Assess: Are they stable enough to go in? Or do they need Mental Health support first?\n• If stable: \"When you're ready, we'll call you in.\"\n• If unstable: Coordinate with Mental Health team\n\n**Challenge: Technical issue in ballroom (table breaks, sound system fails)**\n• Ballroom Lead handles immediate issue\n• Outside Lead pauses entry: \"We're having a brief technical issue. Just 5 more minutes.\"\n• Both Leads communicate to adjust timing\n• Keep HealEEs informed without alarming them\n\n**Challenge: Flow is too slow (bottleneck)**\n• Inside and Outside Leads coordinate: \"What's causing delay?\"\n• Troubleshoot: Is entry too slow? Are Healers taking longer than expected? Is exit unclear?\n• Adjust flow: Maybe smaller groups, more time between rounds, clearer exit instructions\n• Communicate changes to maintain smooth experience\n\n---\n\n**KEY PRINCIPLES FOR CH COORDINATION EXCELLENCE:**\n\n• **Sacred service:** You're supporting profound healing, not just managing logistics\n• **Grounded calm:** Your nervous system affects anxious HealEEs—stay steady\n• **Invisible orchestration:** Smooth flow feels effortless when done perfectly\n• **Constant communication:** Inside and Outside Leads coordinate continuously\n• **Serve others' transformation:** This is advanced consciousness work—giving without receiving\n\nCoherence Healing coordination is where devotional service meets logistical precision. Where organization becomes sacred. Where your invisible excellence holds space for someone else's miracle.\n\nThat's holy work."
      },
      {
        "title": "Section Leads & Integrating Additional Duties with Primary Roles",
        "content": "**SECTION LEADS: ADDITIONAL LAYER OF SACRED OVERSIGHT**\n\n**The Function:**\nSection Leads provide extra support for Group Leads, especially in large sections (200+ participants).\n\n**Typical responsibilities:**\n• Support Group Lead with section coordination\n• Additional eyes and presence in section during sessions\n• Monitor participant needs Group Lead might miss\n• Communication bridge between Group Lead and support teams\n• Handle minor issues independently, escalate complex ones to Group Lead\n• Backup leadership when Group Lead is occupied elsewhere\n\n**Why this role matters:**\nOne Group Lead managing 200+ people can't see everything simultaneously. Section Lead provides additional oversight, ensuring no participant falls through the cracks.\n\n**The consciousness principle:**\nSection Leads practice leadership without needing the title. You're providing essential support, often doing the same work as Group Lead, but in a support capacity.\n\nThis is ego work: serving without needing recognition. Leading without needing the label.\n\n---\n\n**HOW ADDITIONAL DUTIES INTEGRATE WITH PRIMARY ROLES:**\n\nAdditional Duties are assigned ON TOP OF your primary role. Understanding how they integrate helps you manage dual responsibilities:\n\n**EXAMPLE 1: Group Greeter + Greeter/Room (Room Reset)**\n**Primary role (daytime):** Greet participants in your section, help them find seats, create welcoming energy\n**Additional duty (evening):** Stay late after everyone leaves to help Room Reset Lead position gravity chairs and signs in your section\n**Integration:** You know your section intimately during the day, so you're perfect to set it up at night. Your daytime knowledge informs your evening setup.\n**Time management:** Room Reset is evening work (after sessions end), so it doesn't conflict with daytime Greeter duties\n\n**EXAMPLE 2: HST Member + Meditation Assist**\n**Primary role:** Support HSL with Coherence Healing logistics, coordinate HealEE needs\n**Additional duty:** Serve as MA during certain meditation sessions (not during CH sessions)\n**Integration:** You're scheduled for MA when you're not needed for HST duties. The timing is coordinated so you're not pulled in two directions.\n**Time management:** Communicate your MA schedule clearly so HSL knows when you're unavailable for HST work\n\n**EXAMPLE 3: Door Volunteer + Signs Lead**\n**Primary role:** Coordinate door access team, manage ballroom entry/exit during sessions\n**Additional duty:** Oversee all reserved signage throughout event\n**Integration:** Both roles require attention to detail, tracking, and proactive problem-solving. Signs work can be done between door duties (during sessions when doors are closed).\n**Time management:** Signs checks can happen early morning or during meditation when doors are managed but not actively in flux\n\n**EXAMPLE 4: Group Lead + Section Lead**\n**Sometimes these are the same role** (Group Lead IS the Section Lead)\n**Sometimes Section Lead is additional support FOR the Group Lead** (large sections need both)\n**Integration:** Work collaboratively—Section Lead handles some oversight while Group Lead focuses on coordination, or vice versa\n\n---\n\n**MANAGING DUAL RESPONSIBILITIES:**\n\n**1. Clear communication about availability**\nIf you're assigned both Group Greeter and MA duties, make sure both Teams Leads know:\n• When you're available for each role\n• If there's any timing conflict\n• What your energy capacity is (honest assessment)\n\nDon't silently overextend. Speak up if dual roles are too much.\n\n**2. Prioritize based on timing**\nIf both roles need you simultaneously:\n• Communicate immediately: \"I'm scheduled for MA but also needed for Room Reset—which takes priority?\"\n• Usually one Team Lead will adjust or find coverage\n• Don't try to do both at once—that serves neither role well\n\n**3. Take care of yourself**\nAdditional Duties often mean:\n• Longer hours (Room Reset until midnight + early morning Greeter duty)\n• Higher stress (MA during intense sessions)\n• Less downtime\n\nYou MUST:\n• Eat properly (don't skip meals rushing between duties)\n• Hydrate consistently\n• Sleep when you can (even 20-minute rests matter)\n• Ask for breaks when needed\n• Say no if you're genuinely at capacity\n\n**4. Ask for support when needed**\nIf you're struggling with dual responsibilities:\n• Tell your Team Lead: \"I'm finding the combination of X and Y really demanding. Can we adjust?\"\n• Don't suffer silently—that leads to burnout and poor service in both roles\n• It's better to excel at one role than barely manage two\n\n**5. Recognize your contribution**\nVolunteers who take on Additional Duties are providing extraordinary service.\n\nYou're staying late when others leave. You're serving in high-intensity roles. You're managing complex coordination.\n\nThat deserves acknowledgment—from others and from yourself.\n\nYou're not \"just doing your job.\" You're going above and beyond. Let that land.\n\n---\n\n**THE DEEPER TEACHING OF ADDITIONAL DUTIES:**\n\nAdditional Duties aren't 'extra work' you're burdened with. They're advanced consciousness training you're being trusted with.\n\n**What you're really learning:**\n\n**Through MA:**\nWitnessing without interfering. Holding space without controlling. Trusting process. Being the calm.\n\n**Through Room Reset:**\nServing the invisible. Precision as devotion. Late-night sacrifice. Excellence no one will consciously notice.\n\n**Through CH coordination:**\nOrchestrating transformation you won't experience. Serving others' healing. Logistical grace under pressure.\n\n**Through Section Leads:**\nLeading without the title. Supporting without needing recognition. Ego dissolution through service.\n\nEvery Additional Duty is teaching you:\n• To see energy, not just physical reality\n• To serve without attachment to outcomes or recognition\n• To find meaning in invisible excellence\n• To trust the larger system you're part of\n• To dissolve ego through devotional service\n\nThis IS the work. Not separate from consciousness training. Not preparation for the 'real' spiritual work.\n\nThis is it.\n\nWhen you position a gravity chair at 11 PM with the same precision you'd want if YOU needed that chair—you're embodying service.\n\nWhen you hold space during meditation without needing recognition—you're practicing ego dissolution.\n\nWhen you coordinate healing logistics for someone else's miracle—you're transcending self-centered consciousness.\n\nAdditional Duties are consciousness work wearing a logistics costume.\n\nSee through the costume. Receive the training."
      }
    ],
    "reflection": {
      "title": "The Invisible Foundation",
      "content": "You're learning about the roles no one sees.\n\nThe Meditation Assist standing quietly in the corner. The Room Reset team working at midnight. The Signs Lead checking every detail. The Coherence Healing coordinators orchestrating flow.\n\nThese aren't the celebrated positions. No one applauds when you position a gravity chair perfectly at 11 PM. Participants don't thank you for holding space during their breakthrough—they don't even know you were there.\n\nAnd that's exactly the point.\n\nYou're learning a different kind of service. The kind that finds meaning in the work itself, not in recognition. The kind that serves the invisible. The kind that trusts what can't be measured.\n\nThis is advanced consciousness training.\n\nWhen you set up a room with precision while everyone else sleeps, you're learning embodied care. You're practicing attention to detail as devotion. You're serving people you'll never meet, for outcomes you'll never witness.\n\nWhen you hold space during meditation without interfering, you're learning to witness without controlling. You're practicing presence without agenda. You're trusting process over outcome.\n\nWhen you coordinate someone else's healing journey, you're learning to serve transformation you won't personally experience. You're practicing generosity without return. You're dissolving the boundary between self and other.\n\nThese aren't just tasks. These are teachings.\n\nMost people think spiritual practice happens during meditation. On the cushion. In altered states. In peak experiences.\n\nBut you're learning something deeper: that consciousness work happens everywhere. Especially in the invisible moments. Especially in the unglamorous tasks. Especially when no one's watching.\n\nHow you position a chair at midnight reveals your relationship to service.\n\nHow you hold space without needing recognition reveals your relationship to ego.\n\nHow you coordinate logistics for someone else's miracle reveals your relationship to purpose.\n\nAdditional Duties are consciousness training disguised as logistics.\n\nThe volunteer moving chairs isn't just doing physical labor. They're practicing sacred attention to detail.\n\nThe MA standing silently isn't just monitoring safety. They're embodying grounded presence.\n\nThe CH coordinator isn't just managing flow. They're serving transformation beyond self.\n\nThis is the work.\n\nNot separate from spiritual practice. Not preparation for the 'real' consciousness work.\n\nThis IS it.\n\nWhen you understand this—when you truly feel it—everything changes.\n\nYou stop waiting for the 'important' moments and recognize that every moment is important.\n\nYou stop seeking recognition and find meaning in invisible excellence.\n\nYou stop serving for what you'll get and start serving for what you'll become.\n\nThat's who you're becoming. Someone who sees the sacred in the mundane. Who finds purpose in the invisible. Who serves without needing to be seen.\n\nNot just during this event. In life. In every role. In every moment.\n\nThat's the real training. That's the real transformation."
    },
    "whyThisMatters": {
      "quote": "The moment you decide to be excellent in everything you do, you're already changing.",
      "author": "Dr. Joe Dispenza",
      "content": "**Additional Duties exist because certain functions require specialized focus, training, and often sacrifice.**\n\nYour primary role (Group Greeter, HST member, Door volunteer, etc.) is your foundational responsibility throughout the week. But the event requires additional layers of support that demand:\n\n**Specialized skills:** Meditation Assist requires discernment—knowing when someone's having a breakthrough vs. a crisis. Not everyone has that intuition.\n\n**Timing flexibility:** Room Reset happens after everyone leaves (often until midnight or later). Requires physical stamina and willingness to serve when others are resting.\n\n**Advanced coordination:** Coherence Healing logistics are complex, high-stakes, and demand experienced judgment.\n\n**Extra capacity:** Section Leads provide additional oversight when Group Leads are managing 200+ people.\n\n**Why this chapter matters to YOU:**\n\nEven if you're not assigned Additional Duties at your first event, understanding them transforms how you see the entire system:\n\n**1. Consciousness training lens:**\nThese roles teach you to:\n• See energy, not just physical reality (MA watching for subtle shifts)\n• Serve the invisible (Room Reset perfecting what no one consciously notices)\n• Trust the unseen (holding healing space without attachment to outcomes)\n• Find meaning in service itself, not external recognition\n\n**2. Appreciation of the whole:**\nWhen you understand what the MA was doing during that meditation, what the Room Reset team did until 1 AM, what the Signs Lead tracked all week—you see the architecture. The invisible support structure holding everything.\n\n**3. Integration with your role:**\nYour primary role connects with these roles:\n• Group Greeters work with Room Reset to maintain sections\n• HST coordinates with CH Leads during healing sessions  \n• Door volunteers support MA by managing ballroom access during meditation\n• Everyone benefits from Signs Lead's invisible excellence\n\n**4. Path forward:**\nAdditional Duties are often how experienced volunteers deepen their service. First event: learn your primary role. Later events: maybe you're ready for MA, Room Reset coordination, or CH Lead responsibility.\n\n**The deeper truth:**\nAdditional Duties aren't 'extra work.' They're advanced consciousness training.\n\nWhen you set up gravity chairs at midnight with the same precision you'd want if YOU needed one—that's embodied service.\n\nWhen you hold space during meditation without needing recognition—that's ego dissolution.\n\nWhen you coordinate healing logistics knowing your planning serves someone's sacred breakthrough—that's purpose beyond self.\n\nThis chapter teaches:\n• MA: Witnessing and holding without interfering\n• Room Reset: Sacred attention to physical detail\n• CH Leads: Serving transformation you won't personally experience  \n• Section Leads: Supporting leadership without needing the title\n\nEvery role is consciousness work. These roles just make it more obvious."
    }
  },
  "phase3_integrate": {
    "quiz": [
      {
        "question": "You're serving as Meditation Assist during an afternoon session. A participant in your section is crying—not sobbing loudly, just tears streaming down their face quietly. They seem present, eyes closed, breathing steadily. What do you do?",
        "options": [
          {
            "text": "Hold space silently from your position. Stay grounded. If you make eye contact, offer a soft, supportive gaze, but don't approach or interrupt. This is emotional release, not crisis. Your witnessing presence is the intervention.",
            "isCorrect": true,
            "feedback": "Perfect. You recognized that quiet tears aren't a problem—they're healing. The person seems present and grounded. Approaching them would actually interrupt their process. Your job is to hold calm space, be available if needed, but trust their journey. This is skilled MA work: knowing when NOT to intervene."
          },
          {
            "text": "Approach them quietly and whisper, 'Are you okay? Do you need anything?' Just to make sure they're not in distress.",
            "isCorrect": false,
            "feedback": "Don't interrupt their process unnecessarily. Quiet crying with steady breathing and present body language suggests healing release, not crisis. Your question would pull them out of important work. Hold space from where you are. Only approach if crying escalates to loud sobbing that disrupts others, or if they signal for help."
          },
          {
            "text": "Signal another MA via Telegram to come observe this person with you, so you have backup in case it escalates into something more serious.",
            "isCorrect": false,
            "feedback": "This is overcorrecting. Quiet tears don't require backup or heightened alert. You're creating unnecessary drama around natural emotional release. Trust your discernment. Hold space. Monitor. If it DOES escalate to something concerning, then signal for support. But don't treat normal release as crisis."
          }
        ]
      },
      {
        "question": "You're part of Room Reset team. It's 10:30 PM, and Room Reset Lead has posted detailed instructions in Telegram: 'Blue section: Move 2 gravity chairs to Row 7, Seats 4 and 5. Place reserved signs on Row 3, Seat 9 and Row 12, Seat 6.' You're the Greeter/Room volunteer for Blue section. What do you do?",
        "options": [
          {
            "text": "Read the instructions carefully, then execute exactly as written. Move the 2 gravity chairs to the specified seats, place the reserved signs precisely where indicated. Double-check your work against the instructions. Post in Telegram when complete: 'Blue section Room Reset complete—2 gravity chairs and 2 reserved signs placed per plan.'",
            "isCorrect": true,
            "feedback": "Excellent execution. You read the full instructions, executed precisely, checked your work, and communicated completion. This is exactly what Room Reset requires—following the plan with precision, taking ownership of your section, and keeping the team informed. Clean, clear, complete."
          },
          {
            "text": "Wait for Room Reset Lead to come to your section and show you exactly where the gravity chairs should go—you don't want to place them incorrectly and create a safety issue.",
            "isCorrect": false,
            "feedback": "The detailed instructions were posted precisely so you could execute independently. Room Reset Lead can't personally supervise every section—that's why the plan is specific. Trust the instructions. If something is genuinely unclear, ask for clarification. But don't wait for hand-holding when you have clear direction."
          },
          {
            "text": "Check with your Group Lead first to confirm these changes make sense for Blue section before moving anything—you want to make sure everyone's coordinated on this plan.",
            "isCorrect": false,
            "feedback": "Room Reset Lead already coordinated with Group Leads on the overall plan before posting instructions. By the time you see the instructions, the plan is approved. You don't need to double-check—that creates redundant communication and delays. Trust the system. Follow the posted plan."
          }
        ]
      },
      {
        "question": "You're serving as Meditation Assist when a participant suddenly starts shaking intensely—their whole body jerking rhythmically. They're still in their chair, but it looks like they might slide off. Their eyes are closed. No sounds. What's your immediate response?",
        "options": [
          {
            "text": "Move quickly but calmly to them. Position yourself close enough to support them if they start to fall, but don't restrain the shaking. Clear space around them. Stay grounded. Monitor breathing. If shaking continues beyond 2-3 minutes or escalates, signal Medical. Otherwise, hold space for the release.",
            "isCorrect": true,
            "feedback": "Excellent response. You're protecting them from injury (falling, hitting things) without trying to stop the energetic release (the shaking). You're positioned to help, you're ensuring safety, and you're ready to escalate if needed. This is the perfect balance—protective but not interfering with their process. The shaking is likely profound release, not seizure, given the context and presentation."
          },
          {
            "text": "Immediately signal Medical via Telegram that someone is having a seizure in your section and needs emergency response. Move to them and wait for Medical to arrive.",
            "isCorrect": false,
            "feedback": "Don't automatically label intense shaking as seizure—context matters. This person is in meditation, rhythmic shaking, no loss of consciousness indicators. This is more likely energetic release. Move close, ensure safety, monitor. IF it becomes actual seizure (different quality—usually more violent, loss of awareness, etc.), THEN follow seizure protocol. But don't panic-escalate to Medical for every intense release."
          },
          {
            "text": "Hold your position and observe from where you are. If they fall out of the chair, then you'll approach. Until then, let the process unfold without intervention.",
            "isCorrect": false,
            "feedback": "Too hands-off. While you shouldn't stop the shaking, you also can't let them fall and potentially injure themselves. Move closer. Be ready to catch or support. Prevention of injury IS your job. You can protect them physically while still allowing the energetic release to continue."
          }
        ]
      },
      {
        "question": "You're the CH Outside Ballroom Lead. A HealEE scheduled for the 2 PM session arrives at 2:35 PM—35 minutes late. They're apologetic: 'I got lost. I'm so sorry. Can I still go in?' The 2 PM session is nearly complete, and the 4 PM session is confirmed with space. What do you do?",
        "options": [
          {
            "text": "Respond warmly: 'It's okay—these venues can be confusing. The 2 PM session is almost complete, but you're confirmed for the 4 PM session at this location. Can you return at 3:50 PM? That way you'll get your full healing session.' If they can't come back, coordinate with HSL via Telegram about alternatives.",
            "isCorrect": true,
            "feedback": "Perfect. You were kind (didn't make them feel worse about being late), gave them clear information (2 PM won't work but 4 PM is available), provided specific instructions (return at 3:50 PM), and offered escalation path if needed (coordinate with HSL). This balances compassion with logistics. The HealEE feels cared for, and the system stays intact."
          },
          {
            "text": "Tell the Ballroom Lead you have a late HealEE and ask if you can squeeze them in for the last few minutes of the 2 PM session—better than making them wait until 4 PM.",
            "isCorrect": false,
            "feedback": "Don't disrupt the flow for a late arrival. The 2 PM session has timing, Healer assignments, and flow that's already in progress. Squeezing someone in late creates confusion and undermines the schedule. They have a confirmed 4 PM spot. That's their option. If they truly can't return, then coordinate with HSL for alternatives—but don't jury-rig solutions that affect the current session."
          },
          {
            "text": "'I'm sorry, but the 2 PM session has already started and we can't accommodate late arrivals. You'll need to contact registration to reschedule for another day.'",
            "isCorrect": false,
            "feedback": "Too rigid and dismissive. They HAVE a 4 PM session confirmed—you're not telling them that option. And you're making them feel like they've lost their chance entirely. Be kind. Give them the 4 PM option. If that doesn't work, coordinate with HSL. Don't shut the door without offering alternatives."
          }
        ]
      },
      {
        "question": "You're assigned both Group Greeter (daytime role) and Meditation Assist (during meditation sessions). Tomorrow there's a 6 AM meditation, and you're also scheduled to help with Room Reset tonight starting at 10 PM (expected to go until midnight). This means you'd get roughly 5 hours of sleep if you do both. What do you do?",
        "options": [
          {
            "text": "Message both Team Leads proactively: 'I'm scheduled for Room Reset tonight (10 PM-12 AM) and MA tomorrow at 6 AM. That's a very short night. Can we adjust one of those assignments, or should I prioritize one over the other?' Let them coordinate a solution.",
            "isCorrect": true,
            "feedback": "Excellent self-advocacy and communication. You identified the conflict early, communicated clearly to both Team Leads, and asked for their input on how to handle it. This is mature, responsible, and serves both roles better than silently suffering through exhaustion. Team Leads can adjust—they'd rather know than have you burn out or perform poorly in both roles."
          },
          {
            "text": "Just do both. It's only one night of short sleep. You committed to both roles, and you don't want to let anyone down by backing out now. Push through.",
            "isCorrect": false,
            "feedback": "This is martyr mentality, not service. Exhaustion compromises your performance in both roles. MA requires high alertness—you're responsible for safety. Room Reset requires physical stamina and attention to detail. Running on 5 hours of sleep serves neither role well. Speak up. The system can adjust. Suffering silently helps no one."
          },
          {
            "text": "Skip the Room Reset—MA is more important because it involves safety. Just don't show up tonight and assume someone else will cover your section.",
            "isCorrect": false,
            "feedback": "Don't just no-show. That leaves Room Reset Lead scrambling and your section potentially unfinished. Communicate the conflict to both Team Leads and let THEM decide priorities. Don't unilaterally bail on commitments. If MA truly takes priority, that conversation should happen explicitly with coordination, not by you ghosting Room Reset."
          }
        ]
      }
    ]
  },
  "phase4_anchor": {
    "summary": {
      "keyPoints": [
        "Additional Duties are consciousness training disguised as logistics—you're learning to serve the invisible",
        "Meditation Assist: Hold space in altered states, discern release vs. crisis, intervene only when necessary, stay grounded while others journey",
        "Room Reset: Set the sacred container through physical precision, serve late at night so tomorrow's transformation can unfold",
        "Coherence Healing coordination: Two Leads (Ballroom + Outside) orchestrate healing logistics with devotional attention",
        "Section Leads: Additional oversight layer supporting Group Leads, practicing leadership without needing the title",
        "Additional Duties integrate with primary roles—timing coordinated, communication essential, self-care critical",
        "These roles require sacrifice (late nights, intensity, emotional labor) and offer advanced training (serving unseen, ego dissolution)",
        "Done perfectly, Additional Duties are invisible—participants experience seamless flow, never knowing the coordination behind it"
      ],
      "integration": "You now understand the invisible architecture. The roles that serve by disappearing.\n\nThe Meditation Assist who held space during your breakthrough—you might not have even noticed them. The Room Reset team who worked until 1 AM so your section was perfect the next morning—you'll never know their names. The CH Leads who coordinated your healing session so smoothly you thought it was effortless—their orchestration was invisible.\n\nThat's the mastery.\n\nAdditional Duties teach you:\n• To see energy, not just logistics\n• To serve without attachment to recognition  \n• To find meaning in invisible excellence\n• To trust the process even when you can't control it\n• To dissolve ego through devotional service\n\nThis is consciousness work.\n\nWhen you position a gravity chair with precision at 11 PM—you're practicing embodied care.\n\nWhen you hold space during meditation without interfering—you're learning to witness without controlling.\n\nWhen you coordinate someone else's healing journey—you're serving transformation beyond self.\n\nThese aren't tasks. These are teachings.\n\nIf you're assigned Additional Duties, receive them as the gift they are: advanced training in sacred service.\n\nIf you're not assigned them yet, understand and appreciate those who are. And prepare yourself—one day you might be trusted with this invisible, essential work.\n\nModule 3 complete. You've learned the full architecture: primary roles, Registration Day positions, and Additional Duties.\n\nThe complete system. Every role interconnected. Every function essential.\n\nYou're ready to embody any piece of this sacred service system.\n\nNext: Module 4 deepens into detailed critical protocols—the specific skills that save lives and hold transformation safely."
    },
    "closingQuote": {
      "text": "If you want to change your life, you have to become conscious of what you've been doing unconsciously. Then you have to do something different.",
      "author": "Dr. Joe Dispenza"
    },
    "nextChapter": {
      "title": "Medical Emergency Response",
      "preview": "Comprehensive medical protocols—building on seizures and gravity chairs with complete decision trees for all emergency situations"
    }
  }
}
